pcap_wrapper.cpython-36m-x86_64-linux-gnu.so
pim_dm-1.4.1.dist-info/METADATA
pim_dm-1.4.1.dist-info/RECORD
pim_dm-1.4.1.dist-info/LICENSE
pim_dm-1.4.1.dist-info/top_level.txt
pim_dm-1.4.1.dist-info/WHEEL
pim_dm-1.4.1.dist-info/entry_points.txt
pim_dm.libs/libpcap-828cc380.so.1.5.3
pimdm/Config.py
pimdm/Interface.py
pimdm/utils.py
pimdm/InterfacePIM6.py
pimdm/Run.py
pimdm/__init__.py
pimdm/UnicastRouting.py
pimdm/Kernel.py
pimdm/InterfacePIM.py
pimdm/TestLogger.py
pimdm/Neighbor.py
pimdm/Main.py
pimdm/packet/PacketPimEncodedUnicastAddress.py
pimdm/packet/PacketPimGraftAck.py
pimdm/packet/PacketPimHello.py
pimdm/packet/Packet.py
pimdm/packet/PacketIpHeader.py
pimdm/packet/PacketPimEncodedSourceAddress.py
pimdm/packet/PacketPimJoinPruneMulticastGroup.py
pimdm/packet/PacketPimGraft.py
pimdm/packet/__init__.py
pimdm/packet/PacketPayload.py
pimdm/packet/PacketPimHelloOptions.py
pimdm/packet/PacketPimAssert.py
pimdm/packet/PacketPimJoinPrune.py
pimdm/packet/ReceivedPacket.py
pimdm/packet/PacketPimStateRefresh.py
pimdm/packet/PacketPimEncodedGroupAddress.py
pimdm/packet/PacketPimHeader.py
pimdm/daemon/Daemon.py
pimdm/daemon/__init__.py
pimdm/rwlock/__init__.py
pimdm/rwlock/RWLock.py
pimdm/tree/local_membership.py
pimdm/tree/assert_state.py
pimdm/tree/KernelEntryInterface.py
pimdm/tree/downstream_prune.py
pimdm/tree/tree_interface.py
pimdm/tree/data_packets_socket.py
pimdm/tree/KernelEntry.py
pimdm/tree/originator.py
pimdm/tree/__init__.py
pimdm/tree/tree_if_upstream.py
pimdm/tree/metric.py
pimdm/tree/pim_globals.py
pimdm/tree/tree_if_downstream.py
pimdm/tree/upstream_prune.py
pimdm/custom_timer/RemainingTimer.py
pimdm/custom_timer/__init__.py
